{
  "name": "dsa5-meistertools",
  "title": "DSA5 - MeisterTools",
  "description": "Viele kleine Helferlein, die dem DSA5 Spielleiter auf Foundry VTT das Leben leichter machen sollen.",
  "author": "tyr0mancer",
  "version": "0.3.0",
  "minimumCoreVersion": "0.7.9",
  "compatibleCoreVersion": "0.7.9",
  "languages": [
    {
      "lang": "de",
      "name": "Deutsch",
      "path": "lang/de.json"
    },
    {
      "lang": "en",
      "name": "English",
      "path": "lang/en.json"
    }
  ],
  "styles": [
    "/styles/meistertools.css",
    "/styles/forms.css"
  ],
  "esmodules": [
    "/meistertools.js",
    "/dsa5-probability.js"
  ],
  "packs": [
    {
      "name": "rolltable-names",
      "label": "Namensliste",
      "path": "packs/rolltable-names.db",
      "entity": "RollTable"
    }
  ],
  "dependencies": [
    {
      "name": "dsa5",
      "type": "system"
    }
  ],
  "url": "https://github.com/tyr0mancer/dsa5-meistertools",
  "manifest": "https://raw.githubusercontent.com/tyr0mancer/dsa5-meistertools/master/module.json",
  "download": "https://github.com/tyr0mancer/dsa5-meistertools/archive/refs/tags/0.2.0.zip",
  "bugs": "https://github.com/tyr0mancer/dsa5-meistertools/issues",
  "allowBugReporter": true
}

